cassandra_snap/__init__.py
cassandra_snap/agent.py
cassandra_snap/logging_helper.py
cassandra_snap/main.py
cassandra_snap/snapshotting.py
cassandra_snap/timeout.py
cassandra_snap/utils.py
cassandra_snap-1.2.1.dist-info/DESCRIPTION.rst
cassandra_snap-1.2.1.dist-info/METADATA
cassandra_snap-1.2.1.dist-info/RECORD
cassandra_snap-1.2.1.dist-info/WHEEL
cassandra_snap-1.2.1.dist-info/entry_points.txt
cassandra_snap-1.2.1.dist-info/metadata.json
cassandra_snap-1.2.1.dist-info/top_level.txt
