Metadata-Version: 2.0
Name: cassandra-snap
Version: 1.2.1
Summary: Cassandra snap is a tool to backup cassandra to Amazon S3.
Home-page: http://github.com/gamunu/cassandra_snap
Author: Gamunu Balagalla
Author-email: gamunu.balagalla@gmail.com
License: UNKNOWN
Platform: UNKNOWN
Classifier: Intended Audience :: Developers
Classifier: Intended Audience :: System Administrators
Classifier: Operating System :: OS Independent
Classifier: Topic :: Software Development
Classifier: Development Status :: 5 - Production/Stable
Classifier: License :: OSI Approved :: GNU General Public License (GPL)
Classifier: Natural Language :: English
Classifier: Programming Language :: Python
Classifier: Topic :: Scientific/Engineering :: Mathematics
Classifier: Topic :: Software Development :: Libraries :: Python Modules
Requires-Dist: argparse
Requires-Dist: boto (>=2.29.1)
Requires-Dist: fabric
Requires-Dist: pyyaml
